tests/snbt_deserialize.py
tests/network.py
tests/snbt_serialize.py
rapidnbt-1.3.5.dist-info/RECORD
rapidnbt-1.3.5.dist-info/LICENSE
rapidnbt-1.3.5.dist-info/WHEEL
rapidnbt-1.3.5.dist-info/entry_points.txt
rapidnbt-1.3.5.dist-info/top_level.txt
rapidnbt-1.3.5.dist-info/METADATA
bindings/ByteTag.cpp
bindings/NbtFile.cpp
bindings/ShortTag.cpp
bindings/NativeModule.hpp
bindings/IntArrayTag.cpp
bindings/ListTag.cpp
bindings/CompoundTagVariant.cpp
bindings/DoubleTag.cpp
bindings/FloatTag.cpp
bindings/Tag.cpp
bindings/Enums.cpp
bindings/ByteArrayTag.cpp
bindings/NativeModule.cpp
bindings/IntTag.cpp
bindings/LongArrayTag.cpp
bindings/EndTag.cpp
bindings/CompoundTag.cpp
bindings/StringTag.cpp
bindings/LongTag.cpp
bindings/NBTIO.cpp
rapidnbt/__init__.py
rapidnbt/_NBT.cpython-39-darwin.so
rapidnbt/cli.py
rapidnbt/__main__.py
rapidnbt/__pyinstaller/hook_rapidnbt.py
rapidnbt/__pyinstaller/__init__.py
rapidnbt/_NBT/end_tag.pyi
rapidnbt/_NBT/int_array_tag.pyi
rapidnbt/_NBT/short_tag.pyi
rapidnbt/_NBT/__init__.pyi
rapidnbt/_NBT/nbt_file.pyi
rapidnbt/_NBT/tag_type.pyi
rapidnbt/_NBT/long_tag.pyi
rapidnbt/_NBT/byte_array_tag.pyi
rapidnbt/_NBT/double_tag.pyi
rapidnbt/_NBT/list_tag.pyi
rapidnbt/_NBT/compound_tag.pyi
rapidnbt/_NBT/float_tag.pyi
rapidnbt/_NBT/long_array_tag.pyi
rapidnbt/_NBT/nbtio.pyi
rapidnbt/_NBT/int_tag.pyi
rapidnbt/_NBT/compound_tag_variant.pyi
rapidnbt/_NBT/string_tag.pyi
rapidnbt/_NBT/nbt_compression_level.pyi
rapidnbt/_NBT/nbt_file_format.pyi
rapidnbt/_NBT/byte_tag.pyi
rapidnbt/_NBT/tag.pyi
rapidnbt/_NBT/snbt_format.pyi
rapidnbt/_NBT/nbt_compression_type.pyi
